smbls/__init__.py
smbls/report.py
smbls/smbls.py
smbls/version.py
smbls-3.0.1.dist-info/METADATA
smbls-3.0.1.dist-info/WHEEL
smbls-3.0.1.dist-info/entry_points.txt
smbls-3.0.1.dist-info/licenses/LICENSE
smbls-3.0.1.dist-info/RECORD
